pydatacheck/__init__.py
pydatacheck/configs.py
pydatacheck/data_check_books.py
pydatacheck/data_check_videos.py
pydatacheck/main.py
pydatacheck/route.py
pydatacheck/static.py
pydatacheck-0.0.8.dist-info/LICENSE
pydatacheck-0.0.8.dist-info/METADATA
pydatacheck-0.0.8.dist-info/WHEEL
pydatacheck-0.0.8.dist-info/entry_points.txt
pydatacheck-0.0.8.dist-info/top_level.txt
pydatacheck-0.0.8.dist-info/RECORD
