Metadata-Version: 2.1
Name: pydatacheck
Version: 0.0.8
Summary: Pydatacheck checks yaml data files
Home-page: https://veltzer.github.io/pydatacheck
Download-URL: https://github.com/veltzer/pydatacheck
Author: Mark Veltzer
Author-email: mark.veltzer@gmail.com
Maintainer: Mark Veltzer
Maintainer-email: mark.veltzer@gmail.com
License: MIT
Keywords: yaml,imdb,simania,goodreads
Platform: python3
Classifier: Development Status :: 4 - Beta
Classifier: Environment :: Console
Classifier: Operating System :: OS Independent
Classifier: Programming Language :: Python
Classifier: Programming Language :: Python :: 3
Classifier: Programming Language :: Python :: 3 :: Only
Classifier: Programming Language :: Python :: 3.11
Classifier: Topic :: Utilities
Classifier: License :: OSI Approved :: MIT License
License-File: LICENSE
Requires-Dist: pytconf
Requires-Dist: cinemagoer
Requires-Dist: beautifulsoup4
